split_schedule/__init__.py
split_schedule/errors.py
split_schedule/py.typed
split_schedule/schedule_builder.py
split_schedule/schedule_types.py
split_schedule-0.3.5.dist-info/LICENSE
split_schedule-0.3.5.dist-info/WHEEL
split_schedule-0.3.5.dist-info/METADATA
split_schedule-0.3.5.dist-info/RECORD
