Metadata-Version: 2.1
Name: split-schedule
Version: 0.3.5
Summary: Split schedule into smaller class sizes
Home-page: https://github.com/sanders41/split-schedule
License: MIT
Keywords: schools,schedule
Author: Paul Sanders
Author-email: psanders1@gmail.com
Requires-Python: >=3.8,<4.0
Classifier: Development Status :: 7 - Inactive
Classifier: License :: OSI Approved :: MIT License
Classifier: Operating System :: OS Independent
Classifier: Programming Language :: Python :: 3
Classifier: Programming Language :: Python :: 3.10
Classifier: Programming Language :: Python :: 3.8
Classifier: Programming Language :: Python :: 3.9
Requires-Dist: openpyxl (>=3.0.5,<4.0.0)
Requires-Dist: pandas (>=1.2.2,<2.0.0)
Project-URL: Documentation, https://github.com/sanders41/split-schedule
Project-URL: Repository, https://github.com/sanders41/split-schedule
